mini_dl_ui/__init__.py
mini_dl_ui/_mdu_utils.py
mini_download_ui-1.0.1.dist-info/METADATA
mini_download_ui-1.0.1.dist-info/WHEEL
mini_download_ui-1.0.1.dist-info/top_level.txt
mini_download_ui-1.0.1.dist-info/RECORD
