Metadata-Version: 2.4
Name: mini-download-ui
Version: 1.0.1
Summary: Minimal terminal download UI
Author: Mathys B.
Classifier: Programming Language :: Python :: 3
Classifier: Operating System :: OS Independent
Requires-Python: >=3.8
